testing.common.database-2.0.2-py3.6-nspkg.pth
testing/common/database.py
testing.common.database-2.0.2.dist-info/DESCRIPTION.rst
testing.common.database-2.0.2.dist-info/METADATA
testing.common.database-2.0.2.dist-info/RECORD
testing.common.database-2.0.2.dist-info/WHEEL
testing.common.database-2.0.2.dist-info/metadata.json
testing.common.database-2.0.2.dist-info/namespace_packages.txt
testing.common.database-2.0.2.dist-info/top_level.txt
