Metadata-Version: 2.0
Name: testing.common.database
Version: 2.0.2
Summary: utilities for testing.* packages
Home-page: https://github.com/tk0miya/testing.common.database
Author: Takeshi Komiya
Author-email: i.tkomiya@gmail.com
License: Apache License 2.0
Platform: UNKNOWN
Classifier: Development Status :: 4 - Beta
Classifier: Intended Audience :: Developers
Classifier: License :: OSI Approved :: Apache Software License
Classifier: Programming Language :: Python
Classifier: Programming Language :: Python :: 2
Classifier: Programming Language :: Python :: 2.7
Classifier: Programming Language :: Python :: 3
Classifier: Programming Language :: Python :: 3.4
Classifier: Programming Language :: Python :: 3.5
Classifier: Programming Language :: Python :: 3.6
Classifier: Topic :: Database
Classifier: Topic :: Software Development
Classifier: Topic :: Software Development :: Testing
Provides-Extra: testing
Requires-Dist: nose; extra == 'testing'
